### 一.编程规约

#### (一)命名风格

>8.【强制】POJO类中布尔类型的变量，都不要加is前缀，否则部分框架解析会引起序列化错误。
>
>反例：定义为基本数据类型Boolean isDeleted的属性，它的方法也是isDeleted()，**RPC框架在反向解析的时候，"误以为"对应的属性名称是deleted**，导致属性获取不到，进而抛出异常。

```java
		private boolean isDeleted;

    public boolean isDeleted() {
        return isDeleted;
    }

    public void setDeleted(boolean deleted) {
        isDeleted = deleted;
    }
```

这里，我设置了一个属性isDeleted，并用ide的getter&setter生成相应方法，getter方法就是isDeleted()，**以前没有注意到这点可能会导致RPC框架反向解析的时候会导致问题**，这里马克一下。



#### (三)代码格式

>3.【强制】if/for/while/switch/do等保留字与括号之间都必须加空格

这里以前也没注意到，没有加空格，可能是加空格是想强调下这些保留字吧，同样马克。





>10【推荐】单个方法的总行数不超过80行。
>
>说明：包括方法签名、结束右大括号、注释、空行、回车及任何不可见字符的总行数不超过80行。
>
>正例：代码逻辑愤青红花和绿叶，个性和共性，绿叶逻辑单独出来成为额外方法，**使主干代码更加清晰**；**共性逻辑抽取成为共性方法，便于复用和维护**。

这里说的挺好的，该抽取的一定要抽取，冗长的代码真的不容易看出主干。

在这里我想贴一段Spring中DispatcherServlet的代码，我感觉这段代码的主干就很清晰，不会有别的碎片化代码影响你理清doDispatch()方法的流程：

~~~java
protected void doDispatch(HttpServletRequest request, HttpServletResponse response) throws Exception {
		HttpServletRequest processedRequest = request;
		HandlerExecutionChain mappedHandler = null;
		boolean multipartRequestParsed = false;

		WebAsyncManager asyncManager = WebAsyncUtils.getAsyncManager(request);

		try {
			ModelAndView mv = null;
			Exception dispatchException = null;

			try {
				processedRequest = checkMultipart(request);
				multipartRequestParsed = (processedRequest != request);

				// Determine handler for the current request.
        //获取当前请求的对应 HandlerExecutionChain
				mappedHandler = getHandler(processedRequest);
				if (mappedHandler == null || mappedHandler.getHandler() == null) {
					noHandlerFound(processedRequest, response);
					return;
				}

				// Determine handler adapter for the current request.
        //获取当前请求的对应 HandlerAdapter
				HandlerAdapter ha = getHandlerAdapter(mappedHandler.getHandler());

				// Process last-modified header, if supported by the handler.
				String method = request.getMethod();
				boolean isGet = "GET".equals(method);
				if (isGet || "HEAD".equals(method)) {
					long lastModified = ha.getLastModified(request, mappedHandler.getHandler());
					if (logger.isDebugEnabled()) {
						logger.debug("Last-Modified value for [" + getRequestUri(request) + "] is: " + lastModified);
					}
					if (new ServletWebRequest(request, response).checkNotModified(lastModified) && isGet) {
						return;
					}
				}

				if (!mappedHandler.applyPreHandle(processedRequest, response)) {
					return;
				}

				// Actually invoke the handler.
        //真正调用请求的对应 Handler
				mv = ha.handle(processedRequest, response, mappedHandler.getHandler());

				if (asyncManager.isConcurrentHandlingStarted()) {
					return;
				}

				applyDefaultViewName(processedRequest, mv);
				mappedHandler.applyPostHandle(processedRequest, response, mv);
			}
			catch (Exception ex) {
				dispatchException = ex;
			}
			catch (Throwable err) {
				// As of 4.3, we're processing Errors thrown from handler methods as well,
				// making them available for @ExceptionHandler methods and other scenarios.
				dispatchException = new NestedServletException("Handler dispatch failed", err);
			}
			processDispatchResult(processedRequest, response, mappedHandler, mv, dispatchException);
		}
		catch (Exception ex) {
			triggerAfterCompletion(processedRequest, response, mappedHandler, ex);
		}
		catch (Throwable err) {
			triggerAfterCompletion(processedRequest, response, mappedHandler,
					new NestedServletException("Handler processing failed", err));
		}
		finally {
			if (asyncManager.isConcurrentHandlingStarted()) {
				// Instead of postHandle and afterCompletion
				if (mappedHandler != null) {
					mappedHandler.applyAfterConcurrentHandlingStarted(processedRequest, response);
				}
			}
			else {
				// Clean up any resources used by a multipart request.
				if (multipartRequestParsed) {
					cleanupMultipart(processedRequest);
				}
			}
		}
	}
~~~



#### (四)OOP 规约

>1.【强制】避免通过一个类的对象引用访问此类的静态变量或静态方法，无谓增加编译器解析成本，直接用类名来访问即可。

这里大家一般不会出错，静态元素的访问肯定是通过类名来调用的；

**TODO 只是这里A.staticField和new A().staticField，这两种调用在编译器或者虚拟机层面是具体怎么回事，有待了解**



>2.【强制】所有的覆写方法，必须加@Override注解。
>
>说明：getOnject()与get0bject()的问题。一个是字母的O，一个是数字的0，加@Override可以准确判断是否覆盖成功。另外，如果在抽象类中对方法签名进行修改，其实现类会马上编译报错。

这里，其实加不加@Override注解，如果在抽象类中对方法签名进行修改，实现类也会报错，只不过是只会在类名那里报错，而如果加上@Override注解的话，在类名和方法名那里都会编译报错。



>4.【强制】外部正在调用或者二方库依赖的接口，不允许修改方法名，避免对接口调用方产生影响。**接口过时必须加@Deprecated注解，并清晰地说明采用的新接口或者新服务是什么**。

这里把过时接口的替代方案说明出来还是很有必要的，另外也可以说明下为啥过时，或者基于什么考虑。



>6.【强制】Object的equals方法容易抛空指针异常，应使用常量或确定有值的对象来调用euqals。
>
>正例："test".equals(object);
>
>反例：object.equals("test");
>
>说明：推荐使用java.util.Objects#equals(jdk7引入的工具类)

~~~java
/**
 * Returns true if the arguments are equal to each other and false otherwise. 
 * Consequently,if both arguments are null, 
 * true is returned and if exactly one argument is null, 
 * false is returned. Otherwise, 
 * equality is determined by using the equals method of the first argument.
 */
public static boolean equals(Object a, Object b) {
        return (a == b) || (a != null && a.equals(b));
    }
~~~

这里贴了下Java7引入的Objects.equals()的方法，可以看到，**使用这个工具方法的话，就无须对调用这个方法的对象进行非空校验，也不怕报空指针**。



>7.【强制】所有的相同类型的包装类对象之间值的比较，全部使用equals方法比较。
>
>说明：对于integer var = ? 在-128至127范围内的赋值，Integer对象是在IntegerCache.cache产生，会复用已有对象，这个区间内的Integer值可以直接使用==进行判断，但是这个区间之外的所有数据，都会在堆上产生，并不会复用已有对象，这是一个大坑，推荐使用equals方法进行判断。

~~~java
public static void main(String[] args) {
        Integer n1 = 123;
        Integer n2 = 123;
        Integer n3 = 128;
        Integer n4 = 128;
        Integer n5 = new Integer(122);
        Integer n6 = new Integer(122);

        System.out.println(n1 == n2);//true
        System.out.println(n3 == n4);//false
        System.out.println(n5 == n6);//false
  
        System.out.println("==================分割线====================");

        Short s1 = 120;
        Short s2 = 120;
        Short s3 = 128;
        Short s4 = 128;
        Short s5 = new Short((short)110);
        Short s6 = new Short((short)110);
        System.out.println(s1 == s2);//true
        System.out.println(s3 == s4);//false
        System.out.println(s5 == s6);//false
    }
~~~

这里同样贴一份我自己的测试代码，使用 new操作符的话，不管在不在-128至127的区间，都是会在堆上产生一个新的对象，返回false；使用自动装箱的话，其实走的是valueOf()方法，而在valueOf() 方法中用到了缓存IntegerCache，在区间内的对象都是复用的缓存的对象，返回true；

再贴一份Java中Integer.IntegerCache的源码：

~~~java
private static class IntegerCache {
        static final int low = -128;
        static final int high;
        static final Integer cache[];

        static {
            // high value may be configured by property
            int h = 127;
            String integerCacheHighPropValue =
                sun.misc.VM.getSavedProperty("java.lang.Integer.IntegerCache.high");
            if (integerCacheHighPropValue != null) {
                try {
                    int i = parseInt(integerCacheHighPropValue);
                    i = Math.max(i, 127);
                    // Maximum array size is Integer.MAX_VALUE
                    h = Math.min(i, Integer.MAX_VALUE - (-low) -1);
                } catch( NumberFormatException nfe) {
                    // If the property cannot be parsed into an int, ignore it.
                }
            }
            high = h;

            cache = new Integer[(high - low) + 1];
            int j = low;
            for(int k = 0; k < cache.length; k++)
                cache[k] = new Integer(j++);

            // range [-128, 127] must be interned (JLS7 5.1.7)
            assert IntegerCache.high >= 127;
        }

        private IntegerCache() {}
    }
~~~

再贴一份Integer.valueOf()的源码：

~~~java
public static Integer valueOf(int i) {
        if (i >= IntegerCache.low && i <= IntegerCache.high)
            return IntegerCache.cache[i + (-IntegerCache.low)];
        return new Integer(i);
    }
~~~



>14.【推荐】使用索引访问用String的split方法得到的数组时，需做最后一个分隔符后有无内容的检查，否则会有抛IndexOutOfBoundsException的风险。
>
>说明：
>
>​	String str = "a,b,c,,";
>
>​	String[] arr = str.split(",");
>
>​	//预期结果大于3，结果是3
>
>​	System.out.println(arr.length);//3

这里确实之前没有注意到，如果上面的代码改为：

~~~java
String str = "a,b,c, ,";
str.split(",");
System.out.println(arr.length);//4
~~~

结果就会变成4了。

>18.【推荐】循环体内，字符串的连接方式，使用StringBuilder的append方法进行扩展。
>
>说明：夏利中，反编译出的字节码文件显示每次循环都会new出一个StringBuilder对象，然后进行append操作，最后通过toString方法返回String对象，造成内存资源浪费。
>
>反例：
>
>​	String str = "start";
>
>​	for(int i = 0; i<100; i++){
>
>​		str = str + "hello";
>
>​	}

这里贴下反编译的字节码文件：

~~~java
    		0: ldc           #2                  // String start
         2: astore_1
         3: iconst_0
         4: istore_2
         5: iload_2
         6: bipush        100
         8: if_icmpge     37
        11: new           #3                  // class java/lang/StringBuilder
        14: dup
        15: invokespecial #4                  // Method java/lang/StringBuilder."<init>":()V
        18: aload_1
        19: invokevirtual #5                  // Method java/lang/StringBuilder.append:(Ljava/lang/String;)Ljava/lang/StringBuilder;
        22: ldc           #6                  // String hello
        24: invokevirtual #5                  // Method java/lang/StringBuilder.append:(Ljava/lang/String;)Ljava/lang/StringBuilder;
        27: invokevirtual #7                  // Method java/lang/StringBuilder.toString:()Ljava/lang/String;
        30: astore_1
        31: iinc          2, 1
        34: goto          5
        37: return
~~~

可以看到，每次循环都new了一个StringBuilder对象，这个new StringBuilder的操作是由Java虚拟机的语法糖实现的，不可避免，但是每次循环都生成一个StringBuilder对象就不太好了。



